src/ESTARFM.py
src/ESTARFM_FAST.py
luisito19963-4.3.dist-info/METADATA
luisito19963-4.3.dist-info/WHEEL
luisito19963-4.3.dist-info/top_level.txt
luisito19963-4.3.dist-info/RECORD
