Metadata-Version: 2.1
Name: luisito19963
Version: 4.3
Summary: my description
Home-page: UNKNOWN
Author: Luis bravo
Author-email: luisbravocollado@gmail.com
License: UNKNOWN
Keywords: testing,logging,example
Platform: UNKNOWN
Requires-Dist: a (==0.1)
Requires-Dist: a123456aa (==0.1)
Requires-Dist: affine (==2.3.0)
Requires-Dist: alabaster (==0.7.12)
Requires-Dist: appdirs (==1.4.4)
Requires-Dist: argh (==0.26.2)
Requires-Dist: argon2-cffi (==20.1.0)
Requires-Dist: asciitree (==0.3.3)
Requires-Dist: astroid (==2.3.3)
Requires-Dist: astropy (==4.0.1.post1)
Requires-Dist: atomicwrites (==1.4.0)
Requires-Dist: attrs (==19.3.0)
Requires-Dist: Automat (==0.8.0)
Requires-Dist: autopep8 (==1.5.3)
Requires-Dist: Babel (==2.8.0)
Requires-Dist: backcall (==0.2.0)
Requires-Dist: bcrypt (==3.1.7)
Requires-Dist: beautifulsoup4 (==4.9.1)
Requires-Dist: bleach (==3.1.5)
Requires-Dist: bokeh (==2.1.1)
Requires-Dist: Bottleneck (==1.3.2)
Requires-Dist: bravooooooo (==0.1)
Requires-Dist: build (==0.5.0)
Requires-Dist: certifi (==2020.12.5)
Requires-Dist: cffi (==1.14.0)
Requires-Dist: chardet (==3.0.4)
Requires-Dist: click (==7.1.2)
Requires-Dist: click-plugins (==1.1.1)
Requires-Dist: cligj (==0.7.1)
Requires-Dist: cloudpickle (==1.5.0)
Requires-Dist: clyent (==1.2.2)
Requires-Dist: cmarkgfm (==0.4.2)
Requires-Dist: colorama (==0.4.4)
Requires-Dist: conda (==4.10.1)
Requires-Dist: conda-package-handling (==1.7.0)
Requires-Dist: Conjunto-bravo1996 (==0.0.1)
Requires-Dist: constantly (==15.1.0)
Requires-Dist: cryptography (==2.9.2)
Requires-Dist: cssselect (==1.1.0)
Requires-Dist: cvxopt (==1.2.5)
Requires-Dist: cycler (==0.10.0)
Requires-Dist: cytoolz (==0.10.1)
Requires-Dist: dask (==2.20.0)
Requires-Dist: decorator (==4.4.2)
Requires-Dist: defusedxml (==0.6.0)
Requires-Dist: diff-match-patch (==20200713)
Requires-Dist: dill (==0.3.2)
Requires-Dist: distlib (==0.3.1)
Requires-Dist: distributed (==2.20.0)
Requires-Dist: docutils (==0.16)
Requires-Dist: easygui (==0.98.1)
Requires-Dist: entrypoints (==0.3)
Requires-Dist: example1111111-pkg-bravo1996 (==0.0.1)
Requires-Dist: fast-histogram (==0.9)
Requires-Dist: fasteners (==0.16)
Requires-Dist: filelock (==3.0.12)
Requires-Dist: flake8 (==3.8.3)
Requires-Dist: fsspec (==0.7.4)
Requires-Dist: future (==0.18.2)
Requires-Dist: GDAL (==2.3.3)
Requires-Dist: glue-core (==0.15.6)
Requires-Dist: glue-vispy-viewers (==0.12.2)
Requires-Dist: h5py (==2.10.0)
Requires-Dist: HeapDict (==1.0.1)
Requires-Dist: hyperlink (==19.0.0)
Requires-Dist: idlwrap (==0.1.0)
Requires-Dist: idna (==2.9)
Requires-Dist: imageio (==2.9.0)
Requires-Dist: imagesize (==1.2.0)
Requires-Dist: importlib-metadata (==4.5.0)
Requires-Dist: incremental (==17.5.0)
Requires-Dist: intervaltree (==3.0.2)
Requires-Dist: ipykernel (==5.3.3)
Requires-Dist: ipython (==7.16.1)
Requires-Dist: ipython-genutils (==0.2.0)
Requires-Dist: isort (==4.3.21)
Requires-Dist: jedi (==0.17.1)
Requires-Dist: jeepney (==0.4.3)
Requires-Dist: Jinja2 (==2.11.2)
Requires-Dist: joblib (==1.0.1)
Requires-Dist: jsonschema (==3.2.0)
Requires-Dist: jupyter-client (==6.1.6)
Requires-Dist: jupyter-core (==4.6.3)
Requires-Dist: keyring (==21.2.1)
Requires-Dist: kiwisolver (==1.2.0)
Requires-Dist: lazy-object-proxy (==1.5.0)
Requires-Dist: locket (==0.2.0)
Requires-Dist: lpsolve55 (==5.5.0.9)
Requires-Dist: lpsolvers (==0.8.9)
Requires-Dist: luisa (==0.1)
Requires-Dist: lxml (==4.5.2)
Requires-Dist: MarkupSafe (==1.1.1)
Requires-Dist: matplotlib (==3.1.3)
Requires-Dist: mccabe (==0.6.1)
Requires-Dist: mistune (==0.8.4)
Requires-Dist: mkl-fft (==1.1.0)
Requires-Dist: mkl-random (==1.1.1)
Requires-Dist: mkl-service (==2.3.0)
Requires-Dist: monotonic (==1.5)
Requires-Dist: more-itertools (==8.4.0)
Requires-Dist: mpl-scatter-density (==0.6)
Requires-Dist: msgpack (==1.0.0)
Requires-Dist: nbconvert (==5.6.1)
Requires-Dist: nbformat (==5.0.7)
Requires-Dist: networkx (==2.4)
Requires-Dist: notebook (==6.3.0)
Requires-Dist: numcodecs (==0.7.3)
Requires-Dist: numpy (==1.21.0)
Requires-Dist: numpydoc (==1.1.0)
Requires-Dist: olefile (==0.46)
Requires-Dist: packaging (==20.4)
Requires-Dist: pandas (==1.0.5)
Requires-Dist: pandocfilters (==1.4.2)
Requires-Dist: paramiko (==2.7.2)
Requires-Dist: parsel (==1.5.2)
Requires-Dist: parso (==0.7.0)
Requires-Dist: partd (==1.1.0)
Requires-Dist: pathtools (==0.1.2)
Requires-Dist: patsy (==0.5.1)
Requires-Dist: pep517 (==0.10.0)
Requires-Dist: pexpect (==4.8.0)
Requires-Dist: pickleshare (==0.7.5)
Requires-Dist: Pillow (==7.2.0)
Requires-Dist: pipenv (==2020.11.15)
Requires-Dist: pkginfo (==1.7.0)
Requires-Dist: plotly (==4.8.2)
Requires-Dist: pluggy (==0.13.1)
Requires-Dist: prometheus-client (==0.10.1)
Requires-Dist: prompt-toolkit (==3.0.5)
Requires-Dist: psutil (==5.7.0)
Requires-Dist: ptyprocess (==0.6.0)
Requires-Dist: py (==1.9.0)
Requires-Dist: pyasn1 (==0.4.8)
Requires-Dist: pyasn1-modules (==0.2.7)
Requires-Dist: pycddlib (==2.1.2)
Requires-Dist: pycodestyle (==2.6.0)
Requires-Dist: pycosat (==0.6.3)
Requires-Dist: pycparser (==2.20)
Requires-Dist: PyDispatcher (==2.0.5)
Requires-Dist: pydocstyle (==5.0.2)
Requires-Dist: pyflakes (==2.2.0)
Requires-Dist: Pygments (==2.6.1)
Requires-Dist: PyHamcrest (==2.0.2)
Requires-Dist: pylint (==2.4.4)
Requires-Dist: PyMySQL (==0.10.0)
Requires-Dist: PyNaCl (==1.4.0)
Requires-Dist: PyOpenGL (==3.1.1a1)
Requires-Dist: pyOpenSSL (==19.1.0)
Requires-Dist: pyparsing (==2.4.7)
Requires-Dist: pyrsistent (==0.16.0)
Requires-Dist: PySocks (==1.7.1)
Requires-Dist: pytest (==5.4.3)
Requires-Dist: pytest-runner (==5.2)
Requires-Dist: python-dateutil (==2.8.1)
Requires-Dist: python-jsonrpc-server (==0.3.4)
Requires-Dist: python-language-server (==0.34.1)
Requires-Dist: python-utils (==2.5.6)
Requires-Dist: pytz (==2020.1)
Requires-Dist: PyWavelets (==1.1.1)
Requires-Dist: pyxdg (==0.26)
Requires-Dist: PyYAML (==5.3.1)
Requires-Dist: pyzmq (==19.0.1)
Requires-Dist: QDarkStyle (==2.8.1)
Requires-Dist: QtAwesome (==0.7.2)
Requires-Dist: qtconsole (==4.7.5)
Requires-Dist: QtPy (==1.9.0)
Requires-Dist: queuelib (==1.5.0)
Requires-Dist: rasterio (==1.0.21)
Requires-Dist: readme-renderer (==24.0)
Requires-Dist: reportlab (==3.5.49)
Requires-Dist: requests (==2.25.1)
Requires-Dist: requests-toolbelt (==0.9.1)
Requires-Dist: retrying (==1.3.3)
Requires-Dist: rfc3986 (==1.5.0)
Requires-Dist: rope (==0.17.0)
Requires-Dist: Rtree (==0.9.4)
Requires-Dist: ruamel-yaml (==0.15.87)
Requires-Dist: scikit-image (==0.16.2)
Requires-Dist: scikit-learn (==0.24.2)
Requires-Dist: scipy (==1.5.0)
Requires-Dist: Scrapy (==1.6.0)
Requires-Dist: seaborn (==0.10.1)
Requires-Dist: SecretStorage (==3.1.2)
Requires-Dist: Send2Trash (==1.5.0)
Requires-Dist: service-identity (==18.1.0)
Requires-Dist: six (==1.14.0)
Requires-Dist: sklearn (==0.0)
Requires-Dist: snowballstemmer (==2.0.0)
Requires-Dist: snuggs (==1.4.7)
Requires-Dist: sortedcontainers (==2.2.2)
Requires-Dist: soupsieve (==2.0.1)
Requires-Dist: Sphinx (==3.1.2)
Requires-Dist: sphinxcontrib-applehelp (==1.0.2)
Requires-Dist: sphinxcontrib-devhelp (==1.0.2)
Requires-Dist: sphinxcontrib-htmlhelp (==1.0.3)
Requires-Dist: sphinxcontrib-jsmath (==1.0.1)
Requires-Dist: sphinxcontrib-qthelp (==1.0.3)
Requires-Dist: sphinxcontrib-serializinghtml (==1.1.4)
Requires-Dist: spyder (==4.1.4)
Requires-Dist: spyder-kernels (==1.9.2)
Requires-Dist: statsmodels (==0.12.2)
Requires-Dist: tblib (==1.6.0)
Requires-Dist: terminado (==0.9.4)
Requires-Dist: testpath (==0.4.4)
Requires-Dist: threadpoolctl (==2.1.0)
Requires-Dist: toml (==0.10.1)
Requires-Dist: toolz (==0.10.0)
Requires-Dist: tornado (==6.0.4)
Requires-Dist: tqdm (==4.46.0)
Requires-Dist: traitlets (==4.3.3)
Requires-Dist: twine (==3.4.1)
Requires-Dist: Twisted (==20.3.0)
Requires-Dist: typing-extensions (==3.7.4.2)
Requires-Dist: ujson (==1.35)
Requires-Dist: urllib3 (==1.25.8)
Requires-Dist: utils (==1.0.1)
Requires-Dist: virtualenv (==20.4.6)
Requires-Dist: virtualenv-clone (==0.5.4)
Requires-Dist: w3lib (==1.21.0)
Requires-Dist: watchdog (==0.10.3)
Requires-Dist: wcwidth (==0.2.5)
Requires-Dist: webencodings (==0.5.1)
Requires-Dist: wrapt (==1.12.1)
Requires-Dist: wurlitzer (==2.0.1)
Requires-Dist: xlrd (==1.2.0)
Requires-Dist: xmltodict (==0.12.0)
Requires-Dist: yapf (==0.30.0)
Requires-Dist: zarr (==2.8.1)
Requires-Dist: zict (==2.0.0)
Requires-Dist: zipp (==3.1.0)
Requires-Dist: zope.interface (==4.7.1)
